torchexplorer/__init__.py
torchexplorer/core.py
torchexplorer/utils.py
torchexplorer/api/api.py
torchexplorer/api/backend.py
torchexplorer/components/histogram.py
torchexplorer/components/tooltip.py
torchexplorer/hook/hook.py
torchexplorer/render/layout.py
torchexplorer/render/serialize.py
torchexplorer/render/structs.py
torchexplorer/standalone/README.md
torchexplorer/standalone/app.py
torchexplorer/standalone/data/.keep
torchexplorer/standalone/templates/index.html
torchexplorer/structure/structure.py
torchexplorer/vega/.gitignore
torchexplorer/vega/mock_vega_data.py
torchexplorer/vega/prep_vega_dataless.py
torchexplorer/vega/vega_dataless.json
torchexplorer-1.1.2.dist-info/LICENSE
torchexplorer-1.1.2.dist-info/METADATA
torchexplorer-1.1.2.dist-info/WHEEL
torchexplorer-1.1.2.dist-info/top_level.txt
torchexplorer-1.1.2.dist-info/RECORD
