Metadata-Version: 2.1
Name: torchexplorer
Version: 1.1.2
Summary: Interactively inspect pytorch modules during training.
Home-page: https://github.com/spfrommer/torchexplorer
Author: Samuel Pfrommer
Author-email: sam.pfrommer@gmail.com
Requires-Python: >=3.8
License-File: LICENSE
Requires-Dist: torch
Requires-Dist: pygraphviz
Requires-Dist: wandb
Requires-Dist: flask
Requires-Dist: numpy
Requires-Dist: click
Requires-Dist: loguru
Provides-Extra: dev
Requires-Dist: torchvision ; extra == 'dev'
Requires-Dist: lightning ; extra == 'dev'
Requires-Dist: scikit-learn ; extra == 'dev'
Requires-Dist: pytest ; extra == 'dev'
Requires-Dist: pyperclip ; extra == 'dev'
Requires-Dist: mypy ; extra == 'dev'
Requires-Dist: twine ; extra == 'dev'
Requires-Dist: sphinx ; extra == 'dev'
Requires-Dist: furo ; extra == 'dev'
